code_graph_mcp/__init__.py
code_graph_mcp/file_watcher.py
code_graph_mcp/language_router.py
code_graph_mcp/rustworkx_graph.py
code_graph_mcp/server.py
code_graph_mcp/universal_ast.py
code_graph_mcp/universal_graph.py
code_graph_mcp/universal_parser.py
code_graph_mcp-1.2.4.dist-info/METADATA
code_graph_mcp-1.2.4.dist-info/WHEEL
code_graph_mcp-1.2.4.dist-info/entry_points.txt
code_graph_mcp-1.2.4.dist-info/licenses/LICENSE
code_graph_mcp-1.2.4.dist-info/RECORD
