Metadata-Version: 2.4
Name: code-graph-mcp
Version: 1.2.4
Summary: MCP server for multi-language code graph intelligence and analysis across 25+ programming languages
Project-URL: Homepage, https://github.com/entrepeneur4lyf/code-graph-mcp
Project-URL: Repository, https://github.com/entrepeneur4lyf/code-graph-mcp
Project-URL: Documentation, https://github.com/entrepeneur4lyf/code-graph-mcp#readme
Project-URL: Changelog, https://github.com/entrepeneur4lyf/code-graph-mcp/releases
Project-URL: Issues, https://github.com/entrepeneur4lyf/code-graph-mcp/issues
Author-email: entrepeneur4lyf <shawn.payments@gmail.com>
License: MIT License
License-File: LICENSE
Keywords: ast,claude-code,code-analysis,code-quality,complexity-analysis,graph,intelligence,mcp,python,static-analysis
Classifier: Development Status :: 5 - Production/Stable
Classifier: Intended Audience :: Developers
Classifier: License :: OSI Approved :: MIT License
Classifier: Programming Language :: Python :: 3
Classifier: Programming Language :: Python :: 3.12
Classifier: Topic :: Software Development :: Code Generators
Classifier: Topic :: Software Development :: Compilers
Classifier: Topic :: Software Development :: Libraries :: Python Modules
Classifier: Topic :: Software Development :: Quality Assurance
Classifier: Topic :: Text Processing :: Linguistic
Requires-Python: >=3.12
Requires-Dist: anyio>=4.0.0
Requires-Dist: ast-grep-py>=0.39.0
Requires-Dist: click>=8.0.0
Requires-Dist: mcp>=1.12.2
Requires-Dist: rustworkx>=0.15.0
Requires-Dist: watchdog>=6.0.0
Provides-Extra: dev
Requires-Dist: black>=23.0.0; extra == 'dev'
Requires-Dist: pytest-asyncio>=0.23.0; extra == 'dev'
Requires-Dist: pytest>=7.0.0; extra == 'dev'
Requires-Dist: ruff>=0.1.0; extra == 'dev'
Provides-Extra: test
Requires-Dist: pytest-asyncio>=0.23.0; extra == 'test'
Requires-Dist: pytest>=7.0.0; extra == 'test'
